[
    {
        "arguments": [
            "c++",
            "-c",
            "-Wall",
            "-g",
            "-fpermissive",
            "-I./include",
            "-I./deps/date/include",
            "-DMOONLIGHT_ENABLE_STACKTRACE",
            "-DMOONLIGHT_STACKTRACE_IN_DESCRIPTION",
            "--std=c++2a",
            "-g",
            "-o",
            "/home/lainproliant/proj/moonlight/test/slice",
            "test/slice.cpp"
        ],
        "directory": "/home/lainproliant/proj/moonlight",
        "file": "test/slice.cpp"
    },
    {
        "arguments": [
            "c++",
            "-c",
            "-Wall",
            "-g",
            "-fpermissive",
            "-I./include",
            "-I./deps/date/include",
            "-DMOONLIGHT_ENABLE_STACKTRACE",
            "-DMOONLIGHT_STACKTRACE_IN_DESCRIPTION",
            "--std=c++2a",
            "-g",
            "-o",
            "/home/lainproliant/proj/moonlight/test/date",
            "test/date.cpp"
        ],
        "directory": "/home/lainproliant/proj/moonlight",
        "file": "test/date.cpp"
    },
    {
        "arguments": [
            "c++",
            "-c",
            "-Wall",
            "-g",
            "-fpermissive",
            "-I./include",
            "-I./deps/date/include",
            "-DMOONLIGHT_ENABLE_STACKTRACE",
            "-DMOONLIGHT_STACKTRACE_IN_DESCRIPTION",
            "--std=c++2a",
            "-g",
            "-o",
            "/home/lainproliant/proj/moonlight/test/test",
            "test/test.cpp"
        ],
        "directory": "/home/lainproliant/proj/moonlight",
        "file": "test/test.cpp"
    },
    {
        "arguments": [
            "c++",
            "-c",
            "-Wall",
            "-g",
            "-fpermissive",
            "-I./include",
            "-I./deps/date/include",
            "-DMOONLIGHT_ENABLE_STACKTRACE",
            "-DMOONLIGHT_STACKTRACE_IN_DESCRIPTION",
            "--std=c++2a",
            "-g",
            "-o",
            "/home/lainproliant/proj/moonlight/test/file",
            "test/file.cpp"
        ],
        "directory": "/home/lainproliant/proj/moonlight",
        "file": "test/file.cpp"
    },
    {
        "arguments": [
            "c++",
            "-c",
            "-Wall",
            "-g",
            "-fpermissive",
            "-I./include",
            "-I./deps/date/include",
            "-DMOONLIGHT_ENABLE_STACKTRACE",
            "-DMOONLIGHT_STACKTRACE_IN_DESCRIPTION",
            "--std=c++2a",
            "-g",
            "-o",
            "/home/lainproliant/proj/moonlight/test/automata",
            "test/automata.cpp"
        ],
        "directory": "/home/lainproliant/proj/moonlight",
        "file": "test/automata.cpp"
    },
    {
        "arguments": [
            "c++",
            "-c",
            "-Wall",
            "-g",
            "-fpermissive",
            "-I./include",
            "-I./deps/date/include",
            "-DMOONLIGHT_ENABLE_STACKTRACE",
            "-DMOONLIGHT_STACKTRACE_IN_DESCRIPTION",
            "--std=c++2a",
            "-g",
            "-o",
            "/home/lainproliant/proj/moonlight/test/json",
            "test/json.cpp"
        ],
        "directory": "/home/lainproliant/proj/moonlight",
        "file": "test/json.cpp"
    },
    {
        "arguments": [
            "c++",
            "-c",
            "-Wall",
            "-g",
            "-fpermissive",
            "-I./include",
            "-I./deps/date/include",
            "-DMOONLIGHT_ENABLE_STACKTRACE",
            "-DMOONLIGHT_STACKTRACE_IN_DESCRIPTION",
            "--std=c++2a",
            "-g",
            "-o",
            "/home/lainproliant/proj/moonlight/test/shlex",
            "test/shlex.cpp"
        ],
        "directory": "/home/lainproliant/proj/moonlight",
        "file": "test/shlex.cpp"
    },
    {
        "arguments": [
            "c++",
            "-c",
            "-Wall",
            "-g",
            "-fpermissive",
            "-I./include",
            "-I./deps/date/include",
            "-DMOONLIGHT_ENABLE_STACKTRACE",
            "-DMOONLIGHT_STACKTRACE_IN_DESCRIPTION",
            "--std=c++2a",
            "-g",
            "-o",
            "/home/lainproliant/proj/moonlight/test/time",
            "test/time.cpp"
        ],
        "directory": "/home/lainproliant/proj/moonlight",
        "file": "test/time.cpp"
    },
    {
        "arguments": [
            "c++",
            "-c",
            "-Wall",
            "-g",
            "-fpermissive",
            "-I./include",
            "-I./deps/date/include",
            "-DMOONLIGHT_ENABLE_STACKTRACE",
            "-DMOONLIGHT_STACKTRACE_IN_DESCRIPTION",
            "--std=c++2a",
            "-g",
            "-o",
            "/home/lainproliant/proj/moonlight/test/cli",
            "test/cli.cpp"
        ],
        "directory": "/home/lainproliant/proj/moonlight",
        "file": "test/cli.cpp"
    },
    {
        "arguments": [
            "c++",
            "-c",
            "-Wall",
            "-g",
            "-fpermissive",
            "-I./include",
            "-I./deps/date/include",
            "-DMOONLIGHT_ENABLE_STACKTRACE",
            "-DMOONLIGHT_STACKTRACE_IN_DESCRIPTION",
            "--std=c++2a",
            "-g",
            "-o",
            "/home/lainproliant/proj/moonlight/test/string",
            "test/string.cpp"
        ],
        "directory": "/home/lainproliant/proj/moonlight",
        "file": "test/string.cpp"
    },
    {
        "arguments": [
            "c++",
            "-c",
            "-Wall",
            "-g",
            "-fpermissive",
            "-I./include",
            "-I./deps/date/include",
            "-DMOONLIGHT_ENABLE_STACKTRACE",
            "-DMOONLIGHT_STACKTRACE_IN_DESCRIPTION",
            "--std=c++2a",
            "-g",
            "-o",
            "/home/lainproliant/proj/moonlight/test/color",
            "test/color.cpp"
        ],
        "directory": "/home/lainproliant/proj/moonlight",
        "file": "test/color.cpp"
    },
    {
        "arguments": [
            "c++",
            "-c",
            "-Wall",
            "-g",
            "-fpermissive",
            "-I./include",
            "-I./deps/date/include",
            "-DMOONLIGHT_ENABLE_STACKTRACE",
            "-DMOONLIGHT_STACKTRACE_IN_DESCRIPTION",
            "--std=c++2a",
            "-g",
            "-o",
            "/home/lainproliant/proj/moonlight/test/linked_map",
            "test/linked_map.cpp"
        ],
        "directory": "/home/lainproliant/proj/moonlight",
        "file": "test/linked_map.cpp"
    },
    {
        "arguments": [
            "c++",
            "-c",
            "-Wall",
            "-g",
            "-fpermissive",
            "-I./include",
            "-I./deps/date/include",
            "-DMOONLIGHT_ENABLE_STACKTRACE",
            "-DMOONLIGHT_STACKTRACE_IN_DESCRIPTION",
            "--std=c++2a",
            "-g",
            "-o",
            "/home/lainproliant/proj/moonlight/test/core",
            "test/core.cpp"
        ],
        "directory": "/home/lainproliant/proj/moonlight",
        "file": "test/core.cpp"
    },
    {
        "arguments": [
            "c++",
            "-c",
            "-Wall",
            "-g",
            "-fpermissive",
            "-I./include",
            "-I./deps/date/include",
            "-DMOONLIGHT_ENABLE_STACKTRACE",
            "-DMOONLIGHT_STACKTRACE_IN_DESCRIPTION",
            "--std=c++2a",
            "-g",
            "-o",
            "/home/lainproliant/proj/moonlight/test/generator",
            "test/generator.cpp"
        ],
        "directory": "/home/lainproliant/proj/moonlight",
        "file": "test/generator.cpp"
    },
    {
        "arguments": [
            "c++",
            "-c",
            "-Wall",
            "-g",
            "-fpermissive",
            "-I./include",
            "-I./deps/date/include",
            "-DMOONLIGHT_ENABLE_STACKTRACE",
            "-DMOONLIGHT_STACKTRACE_IN_DESCRIPTION",
            "--std=c++2a",
            "-g",
            "-o",
            "/home/lainproliant/proj/moonlight/test/classify",
            "test/classify.cpp"
        ],
        "directory": "/home/lainproliant/proj/moonlight",
        "file": "test/classify.cpp"
    },
    {
        "arguments": [
            "c++",
            "-c",
            "-Wall",
            "-g",
            "-fpermissive",
            "-I./include",
            "-I./deps/date/include",
            "-DMOONLIGHT_ENABLE_STACKTRACE",
            "-DMOONLIGHT_STACKTRACE_IN_DESCRIPTION",
            "--std=c++2a",
            "-g",
            "-o",
            "/home/lainproliant/proj/moonlight/test/lex",
            "test/lex.cpp"
        ],
        "directory": "/home/lainproliant/proj/moonlight",
        "file": "test/lex.cpp"
    },
    {
        "arguments": [
            "c++",
            "-c",
            "-Wall",
            "-g",
            "-fpermissive",
            "-I./include",
            "-I./deps/date/include",
            "-DMOONLIGHT_ENABLE_STACKTRACE",
            "-DMOONLIGHT_STACKTRACE_IN_DESCRIPTION",
            "--std=c++2a",
            "-g",
            "-o",
            "/home/lainproliant/proj/moonlight/test/ansi",
            "test/ansi.cpp"
        ],
        "directory": "/home/lainproliant/proj/moonlight",
        "file": "test/ansi.cpp"
    }
]